odoo8_addon_sale_order_back2draft-8.0.1.0.0.99.dev17-py3.8-nspkg.pth
odoo_addons/sale_order_back2draft/README.rst
odoo_addons/sale_order_back2draft/__init__.py
odoo_addons/sale_order_back2draft/__openerp__.py
odoo_addons/sale_order_back2draft/i18n/ca.po
odoo_addons/sale_order_back2draft/i18n/de.po
odoo_addons/sale_order_back2draft/i18n/es.po
odoo_addons/sale_order_back2draft/i18n/es_ES.po
odoo_addons/sale_order_back2draft/i18n/fi.po
odoo_addons/sale_order_back2draft/i18n/fr.po
odoo_addons/sale_order_back2draft/i18n/hr.po
odoo_addons/sale_order_back2draft/i18n/hu.po
odoo_addons/sale_order_back2draft/i18n/it.po
odoo_addons/sale_order_back2draft/i18n/nl.po
odoo_addons/sale_order_back2draft/i18n/nl_NL.po
odoo_addons/sale_order_back2draft/i18n/pt_BR.po
odoo_addons/sale_order_back2draft/i18n/ro.po
odoo_addons/sale_order_back2draft/i18n/sale_order_back2draft.pot
odoo_addons/sale_order_back2draft/i18n/sk.po
odoo_addons/sale_order_back2draft/i18n/sl.po
odoo_addons/sale_order_back2draft/i18n/tr.po
odoo_addons/sale_order_back2draft/i18n/tr_TR.po
odoo_addons/sale_order_back2draft/i18n/zh_CN.po
odoo_addons/sale_order_back2draft/models/__init__.py
odoo_addons/sale_order_back2draft/models/sale_order.py
odoo_addons/sale_order_back2draft/static/description/icon.png
odoo_addons/sale_order_back2draft/views/sale_order_view.xml
odoo8_addon_sale_order_back2draft-8.0.1.0.0.99.dev17.dist-info/METADATA
odoo8_addon_sale_order_back2draft-8.0.1.0.0.99.dev17.dist-info/WHEEL
odoo8_addon_sale_order_back2draft-8.0.1.0.0.99.dev17.dist-info/namespace_packages.txt
odoo8_addon_sale_order_back2draft-8.0.1.0.0.99.dev17.dist-info/top_level.txt
odoo8_addon_sale_order_back2draft-8.0.1.0.0.99.dev17.dist-info/RECORD
