Metadata-Version: 2.1
Name: odoo8-addon-sale-order-back2draft
Version: 8.0.1.0.0.99.dev17
Summary: Back to draft on sales orders
Home-page: http://www.serviciosbaeza.com
Author: Serv. Tecnol. Avanzados - Pedro M. Baeza
License: UNKNOWN
Platform: UNKNOWN
Classifier: Programming Language :: Python
Classifier: Framework :: Odoo
Classifier: Framework :: Odoo :: 8.0
Requires-Python: ~=2.7
Requires-Dist: odoo (<9.0a,>=8.0a)
